bump2release/__init__.py
bump2release/cli.py
bump2release/constants.py
bump2release/exceptions.py
bump2release/release_flow.py
bump2release/utilities/__init__.py
bump2release/utilities/b2v_handler.py
bump2release/utilities/colorama_handler.py
bump2release/utilities/file_reader.py
bump2release/utilities/git_actions.py
bump2release/utilities/subprocess_handler.py
bump2release-0.2.1.dist-info/LICENSE
bump2release-0.2.1.dist-info/METADATA
bump2release-0.2.1.dist-info/WHEEL
bump2release-0.2.1.dist-info/entry_points.txt
bump2release-0.2.1.dist-info/top_level.txt
bump2release-0.2.1.dist-info/RECORD
