Metadata-Version: 2.1
Name: bump2release
Version: 0.2.1
Summary: Extension of Bump2version to push release tag to git remote
Home-page: https://github.com/katzy687/bump2release
Author: Natti Katz
Author-email: katzy687@gmail.com
License: MIT
Classifier: Programming Language :: Python :: 3.9
Classifier: License :: OSI Approved :: MIT License
Classifier: Operating System :: OS Independent
Requires-Python: >=3.9
License-File: LICENSE
Requires-Dist: bump2version
Requires-Dist: colorama
